{
  "version": "1.0.0",
  "last_updated": "2025-12-20T10:00:00Z",
  "plugins": {
    "arg-board": {
      "name": "Tablero de Juego ARG Transmedia",
      "version": "1.0.0",
      "description": "Motor conversacional para juegos de Realidad Alternativa (ARG) sobre tableros transmedia",
      "author": "Casa Arrakis",
      "installed_at": "2025-12-20T10:00:00Z",
      "enabled": true,
      "agents_count": 8,
      "prompts_count": 67,
      "handoffs": [
        {
          "label": "Abrir Teatro ARG",
          "agent": "Arrakis"
        },
        {
          "label": "Consultar BOE del juego",
          "agent": "BOE"
        },
        {
          "label": "Validar coherencia del tablero",
          "agent": "Decoherence"
        },
        {
          "label": "Generar tablero 3D",
          "agent": "ImpressJS"
        }
      ]
    }
  }
}
